satya/__init__.py
satya/_satya.cpython-311-aarch64-linux-gnu.so
satya/absent.py
satya/array_validator.py
satya/fastapi.py
satya/json_loader.py
satya/json_schema_compiler.py
satya/native_validator.py
satya/profiling.py
satya/rust_model.py
satya/scalar_validators.py
satya/serializers.py
satya/special_types.py
satya/validator.py
satya/validators.py
satya/web.py
satya-0.5.1.dist-info/METADATA
satya-0.5.1.dist-info/WHEEL
satya-0.5.1.dist-info/licenses/LICENSE
satya-0.5.1.dist-info/RECORD
