Metadata-Version: 2.4
Name: satya
Version: 0.5.1
Classifier: Programming Language :: Python :: 3
Classifier: Programming Language :: Python :: 3.9
Classifier: Programming Language :: Python :: 3.10
Classifier: Programming Language :: Python :: 3.11
Classifier: Programming Language :: Python :: 3.12
Classifier: Programming Language :: Python :: 3.13
Classifier: Programming Language :: Python :: 3.14
Classifier: Programming Language :: Rust
Classifier: Development Status :: 5 - Production/Stable
Classifier: License :: OSI Approved :: Apache Software License
Classifier: Operating System :: OS Independent
Classifier: Intended Audience :: Developers
Classifier: Topic :: Software Development :: Libraries :: Python Modules
License-File: LICENSE
Summary: The fastest Python validation library — up to 9× faster than Pydantic v2, powered by Rust
Author: Rach Pradhan
Requires-Python: >=3.9
Project-URL: Bug Tracker, https://github.com/rachpradhan/satya/issues
Project-URL: Documentation, https://github.com/rachpradhan/satya/blob/main/README.md
Project-URL: Homepage, https://github.com/rachpradhan/satya
Project-URL: Repository, https://github.com/rachpradhan/satya
